chord_romanizer/__init__.py
chord_romanizer/chord_interpreter.py
chord_romanizer/chord_parser.py
chord_romanizer/chord_structure.py
chord_romanizer/note_speller.py
chord_romanizer/romanizer.py
chord_romanizer-0.1.3.dist-info/LICENSE
chord_romanizer-0.1.3.dist-info/METADATA
chord_romanizer-0.1.3.dist-info/WHEEL
chord_romanizer-0.1.3.dist-info/top_level.txt
chord_romanizer-0.1.3.dist-info/RECORD
