Metadata-Version: 2.1
Name: chord_romanizer
Version: 0.1.3
Summary: A library to analyze chord progressions and convert them to Roman numeral analysis.
Home-page: https://github.com/anime-song/chord-romanizer
Author: anime-song
Classifier: Programming Language :: Python :: 3
Classifier: License :: OSI Approved :: MIT License
Classifier: Operating System :: OS Independent
Requires-Python: >=3.7
License-File: LICENSE
